pyseaflux/__init__.py
pyseaflux/_version.py
pyseaflux/area.py
pyseaflux/auxiliary_equations.py
pyseaflux/fco2_pco2_conversion.py
pyseaflux/flux_calculations.py
pyseaflux/gas_transfer_velocity.py
pyseaflux/solubility.py
pyseaflux/vapour_pressure.py
pyseaflux/data/__init__.py
pyseaflux/data/aux_vars.py
pyseaflux/data/config.py
pyseaflux/data/download_zenodo_files.py
pyseaflux/data/jra55.py
pyseaflux/data/main.py
pyseaflux/data/pco2atm.py
pyseaflux/data/spco2.py
pyseaflux/data/utils.py
pyseaflux/data/zenodo.yml
tests/__init__.py
tests/test_PyCO2SYS.py
tests/test_conversions.py
tests/test_fluxes.py
pyseaflux-2.2.1.dist-info/LICENSE.txt
pyseaflux-2.2.1.dist-info/METADATA
pyseaflux-2.2.1.dist-info/WHEEL
pyseaflux-2.2.1.dist-info/top_level.txt
pyseaflux-2.2.1.dist-info/RECORD
